urlwait.py
urlwait-1.0.dist-info/LICENSE
urlwait-1.0.dist-info/METADATA
urlwait-1.0.dist-info/WHEEL
urlwait-1.0.dist-info/entry_points.txt
urlwait-1.0.dist-info/top_level.txt
urlwait-1.0.dist-info/RECORD
