Metadata-Version: 2.1
Name: urlwait
Version: 1.0
Summary: A CLI utility for blocking until a service is listening
Home-page: https://github.com/pmac/urlwait
Author: Paul McLanahan
Author-email: paul@mclanahan.net
License: MIT
Keywords: database_url,tcp,port,docker,service,deploy,deployment
Platform: UNKNOWN
Classifier: Development Status :: 3 - Alpha
Classifier: Intended Audience :: Developers
Classifier: Intended Audience :: System Administrators
Classifier: License :: OSI Approved :: MIT License
Classifier: Programming Language :: Python :: 3
Classifier: Programming Language :: Python :: 3.6
Classifier: Programming Language :: Python :: 3.7
Classifier: Programming Language :: Python :: 3.8
Classifier: Topic :: System :: Systems Administration
